molecule_attention_transformer/__init__.py
molecule_attention_transformer/molecule_attention_transformer.py
molecule_attention_transformer-0.0.4.dist-info/LICENSE
molecule_attention_transformer-0.0.4.dist-info/METADATA
molecule_attention_transformer-0.0.4.dist-info/WHEEL
molecule_attention_transformer-0.0.4.dist-info/top_level.txt
molecule_attention_transformer-0.0.4.dist-info/RECORD
